neurosity/__init__.py
neurosity/config.py
neurosity/neurosity.py
neurosity-2.1.1.dist-info/LICENSE
neurosity-2.1.1.dist-info/METADATA
neurosity-2.1.1.dist-info/WHEEL
neurosity-2.1.1.dist-info/top_level.txt
neurosity-2.1.1.dist-info/RECORD
