Metadata-Version: 2.1
Name: neurosity
Version: 2.1.1
Summary: Official Neurosity Python SDK
Home-page: https://github.com/neurosity/neurosity-sdk-python
Author: Alex Castillo
License: MIT
Classifier: Programming Language :: Python :: 3
Classifier: License :: OSI Approved :: MIT License
Classifier: Operating System :: OS Independent
Requires-Python: >=3.8
License-File: LICENSE
Requires-Dist: firebase-rest-api
